rosimport/__init__.py
rosimport/_ros_directory_finder.py
rosimport/_ros_generator.py
rosimport/_rosdef_loader.py
rosimport/_utils.py
rosimport/_version.py
rosimport/rosmsg_metafinder.py
rosimport-0.4.0.dist-info/DESCRIPTION.rst
rosimport-0.4.0.dist-info/METADATA
rosimport-0.4.0.dist-info/RECORD
rosimport-0.4.0.dist-info/WHEEL
rosimport-0.4.0.dist-info/metadata.json
rosimport-0.4.0.dist-info/top_level.txt
